scaffold/__init__.py
scaffold/ui.py
scaffold/web.py
scaffold/base/config.py
scaffold/base/run.py
scaffold/base/app/__init__.py
scaffold/base/app/forms/__init__.py
scaffold/base/app/forms/_action.py
scaffold/base/app/forms/user.py
scaffold/base/app/models/__init__.py
scaffold/base/app/models/user.py
scaffold/base/app/static/css/custom.css
scaffold/base/app/templates/_form_element_horizontal.html
scaffold/base/app/templates/_form_element_vertical.html
scaffold/base/app/templates/_layout.html
scaffold/base/app/templates/_line_counter.html
scaffold/base/app/templates/_pagination.html
scaffold/base/app/templates/_search_widget.html
scaffold/base/app/templates/_table_records.html
scaffold/base/app/templates/about.html
scaffold/base/app/templates/index.html
scaffold/base/app/templates/role.html
scaffold/base/app/templates/role_list.html
scaffold/base/app/templates/user.html
scaffold/base/app/templates/user_list.html
scaffold/base/app/templates/security/change_password.html
scaffold/base/app/templates/security/forgot_password.html
scaffold/base/app/templates/security/login_user.html
scaffold/base/app/templates/security/register_user.html
scaffold/base/app/templates/security/reset_password.html
scaffold/base/app/views/__init__.py
scaffold/base/app/views/user.py
scaffold/base/instance/config.py
scaffold/stubs/form.py.jinja2
scaffold/stubs/template_detail.html.jinja2
scaffold/stubs/template_list.html.jinja2
scaffold/stubs/view.py.jinja2
flask_scaffolding-0.0.29.dist-info/LICENSE
flask_scaffolding-0.0.29.dist-info/METADATA
flask_scaffolding-0.0.29.dist-info/WHEEL
flask_scaffolding-0.0.29.dist-info/top_level.txt
flask_scaffolding-0.0.29.dist-info/RECORD
